grid_weights-0.2.0.dist-info/METADATA
grid_weights-0.2.0.dist-info/WHEEL
grid_weights/conservative.py
grid_weights/tests/test_api.py
grid_weights/tests/test_conservative.py
grid_weights/__init__.py
grid_weights/api.py
grid_weights/grid_weights.cpython-310-darwin.so
grid_weights-0.2.0.dist-info/RECORD
